Main/keypad_scanner.v
// 4x4 Keypad Scanner using Finite State Machine
// This module scans a 4x4 matrix keypad and outputs the pressed key code

module keypad_scanner(
    input wire clk,           // System clock
    input wire reset,         // Reset signal (active high)
    input wire [3:0] col,     // Column inputs from keypad
    output reg [3:0] row,     // Row outputs to keypad
    output reg [3:0] key_code,// 4-bit code representing pressed key
    output reg key_valid      // High when a valid key press is detected
);

    // FSM State Definitions
    // We need 4 states to scan each row
    parameter SCAN_ROW0 = 2'b00;  // Scan row 0 (top row)
    parameter SCAN_ROW1 = 2'b01;  // Scan row 1
    parameter SCAN_ROW2 = 2'b10;  // Scan row 2  
    parameter SCAN_ROW3 = 2'b11;  // Scan row 3 (bottom row)
    
    // State register to hold current state
    reg [1:0] current_state, next_state;
    
    // Key mapping for 4x4 keypad
    // Standard keypad layout:
    //   Col0  Col1  Col2  Col3
    // Row0: 1    2    3    A
    // Row1: 4    5    6    B  
    // Row2: 7    8    9    C
    // Row3: *    0    #    D
    
    // Internal signals
    reg key_pressed;           // Flag indicating any key is pressed
    reg [3:0] detected_key;    // Temporary storage for detected key
    
    // Sequential logic - State register update
    always @(posedge clk or posedge reset) begin
        if (reset) begin
            current_state <= SCAN_ROW0;  // Start from row 0 after reset
        end else begin
            current_state <= next_state;  // Move to next state
        end
    end
    
    // Combinational logic - Next state logic
    // This determines which state to go to next
    always @(*) begin
        case (current_state)
            SCAN_ROW0: next_state = SCAN_ROW1;  // After row 0, go to row 1
            SCAN_ROW1: next_state = SCAN_ROW2;  // After row 1, go to row 2
            SCAN_ROW2: next_state = SCAN_ROW3;  // After row 2, go to row 3
            SCAN_ROW3: next_state = SCAN_ROW0;  // After row 3, go back to row 0
            default:   next_state = SCAN_ROW0;  // Safety default
        endcase
    end
    
    // Output logic - Row scanning
    // We activate one row at a time by making it LOW (0)
    // while keeping other rows HIGH (1)
    always @(*) begin
        case (current_state)
            SCAN_ROW0: row = 4'b1110;  // Row 0 active (bit 0 = 0), others inactive
            SCAN_ROW1: row = 4'b1101;  // Row 1 active (bit 1 = 0), others inactive  
            SCAN_ROW2: row = 4'b1011;  // Row 2 active (bit 2 = 0), others inactive
            SCAN_ROW3: row = 4'b0111;  // Row 3 active (bit 3 = 0), others inactive
            default:   row = 4'b1111;  // All rows inactive (safety)
        endcase
    end
    
    // Key detection logic
    // Check if any column is LOW (indicating a key press in current row)
    always @(*) begin
        key_pressed = 1'b0;        // Default: no key pressed
        detected_key = 4'b0000;    // Default: no key code
        
        case (current_state)
            SCAN_ROW0: begin
                if (col != 4'b1111) begin      // If any column is LOW
                    key_pressed = 1'b1;
                    case (col)
                        4'b1110: detected_key = 4'b0001;  // Key '1' (Row0,Col0)
                        4'b1101: detected_key = 4'b0010;  // Key '2' (Row0,Col1)
                        4'b1011: detected_key = 4'b0011;  // Key '3' (Row0,Col2)
                        4'b0111: detected_key = 4'b1010;  // Key 'A' (Row0,Col3) - A=10
                        default: detected_key = 4'b0000;  // Invalid
                    endcase
                end
            end
            
            SCAN_ROW1: begin
                if (col != 4'b1111) begin      // If any column is LOW
                    key_pressed = 1'b1;
                    case (col)
                        4'b1110: detected_key = 4'b0100;  // Key '4' (Row1,Col0)
                        4'b1101: detected_key = 4'b0101;  // Key '5' (Row1,Col1)
                        4'b1011: detected_key = 4'b0110;  // Key '6' (Row1,Col2)
                        4'b0111: detected_key = 4'b1011;  // Key 'B' (Row1,Col3) - B=11
                        default: detected_key = 4'b0000;  // Invalid
                    endcase
                end
            end
            
            SCAN_ROW2: begin
                if (col != 4'b1111) begin      // If any column is LOW
                    key_pressed = 1'b1;
                    case (col)
                        4'b1110: detected_key = 4'b0111;  // Key '7' (Row2,Col0)
                        4'b1101: detected_key = 4'b1000;  // Key '8' (Row2,Col1)
                        4'b1011: detected_key = 4'b1001;  // Key '9' (Row2,Col2)
                        4'b0111: detected_key = 4'b1100;  // Key 'C' (Row2,Col3) - C=12
                        default: detected_key = 4'b0000;  // Invalid
                    endcase
                end
            end
            
            SCAN_ROW3: begin
                if (col != 4'b1111) begin      // If any column is LOW
                    key_pressed = 1'b1;
                    case (col)
                        4'b1110: detected_key = 4'b1110;  // Key '*' (Row3,Col0) - *=14
                        4'b1101: detected_key = 4'b0000;  // Key '0' (Row3,Col1)
                        4'b1011: detected_key = 4'b1111;  // Key '#' (Row3,Col2) - #=15
                        4'b0111: detected_key = 4'b1101;  // Key 'D' (Row3,Col3) - D=13
                        default: detected_key = 4'b0000;  // Invalid
                    endcase
                end
            end
        endcase
    end
    
    // Output register update
    // This stores the detected key and validity flag
    always @(posedge clk or posedge reset) begin
        if (reset) begin
            key_code <= 4'b0000;
            key_valid <= 1'b0;
        end else begin
            if (key_pressed) begin
                key_code <= detected_key;  // Store the detected key
                key_valid <= 1'b1;        // Mark as valid
            end else begin
                key_valid <= 1'b0;        // No valid key
                // key_code retains previous value
            end
        end
    end

endmodule

Main/keypad_scanner_tb.v
`timescale 1ns/1ps

// Testbench for 4x4 Keypad Scanner
// This module simulates key presses and verifies the scanner works correctly

module keypad_scanner_tb();

    // Test signals
    reg clk;                    // Clock signal
    reg reset;                  // Reset signal  
    reg [3:0] col;             // Column inputs (simulated keypad columns)
    wire [3:0] row;            // Row outputs from scanner
    wire [3:0] key_code;       // Detected key code
    wire key_valid;            // Key validity flag
    
    // Instantiate the keypad scanner module
    keypad_scanner uut (
        .clk(clk),
        .reset(reset),
        .col(col),
        .row(row),
        .key_code(key_code),
        .key_valid(key_valid)
    );
    
    // Clock generation
    // Create a clock with 10ns period (100MHz frequency)
    initial begin
        clk = 0;
        forever #5 clk = ~clk;  // Toggle every 5ns (10ns period)
    end
    
    // Test stimulus
    initial begin
        // Initialize all signals
        reset = 1;              // Start with reset active
        col = 4'b1111;         // No keys pressed initially (all columns HIGH)
        
        // Display header for simulation output
        $display("Time\tReset\tRow\tCol\tKey_Code\tKey_Valid\tExpected_Key");
        $display("----\t-----\t---\t---\t--------\t---------\t------------");
        
        // Wait for a few clock cycles with reset active
        #20;
        reset = 0;              // Release reset
        
        // Wait for FSM to start scanning
        #40;
        
        // Test Case 1: Press key '1' (Row0, Col0)
        // Wait until scanner is scanning row 0
        wait(row == 4'b1110);   // Wait until row 0 is active
        #2;                     // Small delay for setup
        col = 4'b1110;         // Simulate key '1' press (Col0 goes LOW)
        $display("%t\t%b\t%b\t%b\t%b\t\t%b\t\t1", $time, reset, row, col, key_code, key_valid);
        #20;                    // Hold key press
        col = 4'b1111;         // Release key
        #20;
        
        // Test Case 2: Press key '5' (Row1, Col1)  
        wait(row == 4'b1101);   // Wait until row 1 is active
        #2;
        col = 4'b1101;         // Simulate key '5' press (Col1 goes LOW)
        $display("%t\t%b\t%b\t%b\t%b\t\t%b\t\t5", $time, reset, row, col, key_code, key_valid);
        #20;
        col = 4'b1111;         // Release key
        #20;
        
        // Test Case 3: Press key '9' (Row2, Col2)
        wait(row == 4'b1011);   // Wait until row 2 is active  
        #2;
        col = 4'b1011;         // Simulate key '9' press (Col2 goes LOW)
        $display("%t\t%b\t%b\t%b\t%b\t\t%b\t\t9", $time, reset, row, col, key_code, key_valid);
        #20;
        col = 4'b1111;         // Release key
        #20;
        
        // Test Case 4: Press key 'A' (Row0, Col3)
        wait(row == 4'b1110);   // Wait until row 0 is active
        #2;
        col = 4'b0111;         // Simulate key 'A' press (Col3 goes LOW)
        $display("%t\t%b\t%b\t%b\t%b\t\t%b\t\tA", $time, reset, row, col, key_code, key_valid);
        #20;
        col = 4'b1111;         // Release key
        #20;
        
        // Test Case 5: Press key '0' (Row3, Col1)
        wait(row == 4'b0111);   // Wait until row 3 is active
        #2;
        col = 4'b1101;         // Simulate key '0' press (Col1 goes LOW)
        $display("%t\t%b\t%b\t%b\t%b\t\t%b\t\t0", $time, reset, row, col, key_code, key_valid);
        #20;
        col = 4'b1111;         // Release key
        #20;
        
        // Test Case 6: Press key '#' (Row3, Col2)
        wait(row == 4'b0111);   // Wait until row 3 is active
        #2;
        col = 4'b1011;         // Simulate key '#' press (Col2 goes LOW)
        $display("%t\t%b\t%b\t%b\t%b\t\t%b\t\t#", $time, reset, row, col, key_code, key_valid);
        #20;
        col = 4'b1111;         // Release key
        #40;
        
        // Test Case 7: Test reset functionality
        $display("\nTesting Reset...");
        reset = 1;              // Apply reset
        #20;
        reset = 0;              // Release reset
        #40;
        
        // Test Case 8: Multiple key detection test
        $display("\nTesting scanning cycle without key press...");
        #100;                   // Let it scan for a while without any key press
        
        $display("\nSimulation completed successfully!");
        $finish;
    end
    
    // Monitor all signals continuously
    initial begin
        $monitor("Time=%t | Reset=%b | Row=%b | Col=%b | Key_Code=%b(%d) | Valid=%b", 
                 $time, reset, row, col, key_code, key_code, key_valid);
    end
    
    // Generate VCD file for waveform viewing
    initial begin
        $dumpfile("keypad_scanner.vcd");
        $dumpvars(0, keypad_scanner_tb);
    end
    
    // Task to simulate a key press at specific row and column
    task press_key;
        input [1:0] target_row;  // Which row to press key in
        input [1:0] target_col;  // Which column to press key in
        reg [3:0] expected_row_pattern;
        reg [3:0] col_pattern;
        begin
            // Calculate expected row pattern
            case(target_row)
                2'b00: expected_row_pattern = 4'b1110;
                2'b01: expected_row_pattern = 4'b1101;
                2'b10: expected_row_pattern = 4'b1011;
                2'b11: expected_row_pattern = 4'b0111;
            endcase
            
            // Calculate column pattern
            case(target_col)
                2'b00: col_pattern = 4'b1110;
                2'b01: col_pattern = 4'b1101;
                2'b10: col_pattern = 4'b1011;
                2'b11: col_pattern = 4'b0111;
            endcase
            
            // Wait for the correct row to be scanned
            wait(row == expected_row_pattern);
            #2;
            col = col_pattern;      // Apply key press
            #20;
            col = 4'b1111;         // Release key
            #10;
        end
    endtask

endmodule

Main/keypad_scanner.vcd
$date
	Tue Jun 10 20:46:10 2025
$end
$version
	Icarus Verilog
$end
$timescale
	1ps
$end
$scope module keypad_scanner_tb $end
$var wire 4 ! row [3:0] $end
$var wire 1 " key_valid $end
$var wire 4 # key_code [3:0] $end
$var reg 1 $ clk $end
$var reg 4 % col [3:0] $end
$var reg 1 & reset $end
$scope module uut $end
$var wire 1 $ clk $end
$var wire 4 ' col [3:0] $end
$var wire 1 & reset $end
$var parameter 2 ( SCAN_ROW0 $end
$var parameter 2 ) SCAN_ROW1 $end
$var parameter 2 * SCAN_ROW2 $end
$var parameter 2 + SCAN_ROW3 $end
$var reg 2 , current_state [1:0] $end
$var reg 4 - detected_key [3:0] $end
$var reg 4 . key_code [3:0] $end
$var reg 1 / key_pressed $end
$var reg 1 " key_valid $end
$var reg 2 0 next_state [1:0] $end
$var reg 4 1 row [3:0] $end
$upscope $end
$scope task press_key $end
$var reg 4 2 col_pattern [3:0] $end
$var reg 4 3 expected_row_pattern [3:0] $end
$var reg 2 4 target_col [1:0] $end
$var reg 2 5 target_row [1:0] $end
$upscope $end
$upscope $end
$enddefinitions $end
$comment Show the parameter values. $end
$dumpall
b11 +
b10 *
b1 )
b0 (
$end
#0
$dumpvars
bx 5
bx 4
bx 3
bx 2
b1110 1
b1 0
0/
b0 .
b0 -
b0 ,
b1111 '
1&
b1111 %
0$
b0 #
0"
b1110 !
$end
#5000
1$
#10000
0$
#15000
1$
#20000
0$
0&
#25000
b10 0
b1101 !
b1101 1
b1 ,
1$
#30000
0$
#35000
b1011 !
b1011 1
b11 0
b10 ,
1$
#40000
0$
#45000
b0 0
b111 !
b111 1
b11 ,
1$
#50000
0$
#55000
b1110 !
b1110 1
b1 0
b0 ,
1$
#60000
0$
#62000
b1 -
1/
b1110 %
b1110 '
#65000
b100 -
1/
b10 0
b1101 !
b1101 1
1"
b1 #
b1 .
b1 ,
1$
#70000
0$
#75000
b111 -
1/
b1011 !
b1011 1
b11 0
b10 ,
b100 #
b100 .
1$
#80000
0$
#82000
b0 -
0/
b1111 %
b1111 '
#85000
b0 0
b111 !
b111 1
0"
b11 ,
1$
#90000
0$
#95000
b1110 !
b1110 1
b1 0
b0 ,
1$
#100000
0$
#105000
b10 0
b1101 !
b1101 1
b1 ,
1$
#107000
b101 -
1/
b1101 %
b1101 '
#110000
0$
#115000
b1000 -
1/
b1011 !
b1011 1
b11 0
b10 ,
1"
b101 #
b101 .
1$
#120000
0$
#125000
b0 -
1/
b0 0
b111 !
b111 1
b1000 #
b1000 .
b11 ,
1$
#127000
0/
b1111 %
b1111 '
#130000
0$
#135000
b1110 !
b1110 1
b1 0
b0 ,
0"
1$
#140000
0$
#145000
b10 0
b1101 !
b1101 1
b1 ,
1$
#150000
0$
#155000
b1011 !
b1011 1
b11 0
b10 ,
1$
#157000
b1001 -
1/
b1011 %
b1011 '
#160000
0$
#165000
b1111 -
1/
b0 0
b111 !
b111 1
1"
b1001 #
b1001 .
b11 ,
1$
#170000
0$
#175000
b11 -
1/
b1110 !
b1110 1
b1 0
b0 ,
b1111 #
b1111 .
1$
#177000
b0 -
0/
b1111 %
b1111 '
#180000
0$
#185000
b10 0
b1101 !
b1101 1
0"
b1 ,
1$
#190000
0$
#195000
b1011 !
b1011 1
b11 0
b10 ,
1$
#200000
0$
#205000
b0 0
b111 !
b111 1
b11 ,
1$
#210000
0$
#215000
b1110 !
b1110 1
b1 0
b0 ,
1$
#217000
b1010 -
1/
b111 %
b111 '
#220000
0$
#225000
b1011 -
1/
b10 0
b1101 !
b1101 1
1"
b1010 #
b1010 .
b1 ,
1$
#230000
0$
#235000
b1100 -
1/
b1011 !
b1011 1
b11 0
b10 ,
b1011 #
b1011 .
1$
#237000
b0 -
0/
b1111 %
b1111 '
#240000
0$
#245000
b0 0
b111 !
b111 1
0"
b11 ,
1$
#250000
0$
#255000
b1110 !
b1110 1
b1 0
b0 ,
1$
#260000
0$
#265000
b10 0
b1101 !
b1101 1
b1 ,
1$
#270000
0$
#275000
b1011 !
b1011 1
b11 0
b10 ,
1$
#280000
0$
#285000
b0 0
b111 !
b111 1
b11 ,
1$
#287000
1/
b1101 %
b1101 '
#290000
0$
#295000
b10 -
1/
b1110 !
b1110 1
b1 0
b0 ,
1"
b0 #
b0 .
1$
#300000
0$
#305000
b101 -
1/
b10 0
b1101 !
b1101 1
b10 #
b10 .
b1 ,
1$
#307000
b0 -
0/
b1111 %
b1111 '
#310000
0$
#315000
b1011 !
b1011 1
b11 0
b10 ,
0"
1$
#320000
0$
#325000
b0 0
b111 !
b111 1
b11 ,
1$
#329000
b1111 -
1/
b1011 %
b1011 '
#330000
0$
#335000
b11 -
1/
b1110 !
b1110 1
b1 0
b0 ,
1"
b1111 #
b1111 .
1$
#340000
0$
#345000
b110 -
1/
b10 0
b1101 !
b1101 1
b11 #
b11 .
b1 ,
1$
#349000
b0 -
0/
b1111 %
b1111 '
#350000
0$
#355000
b1011 !
b1011 1
b11 0
b10 ,
0"
1$
#360000
0$
#365000
b0 0
b111 !
b111 1
b11 ,
1$
#370000
0$
#375000
b1110 !
b1110 1
b1 0
b0 ,
1$
#380000
0$
#385000
b10 0
b1101 !
b1101 1
b1 ,
1$
#389000
b1110 !
b1110 1
b1 0
b0 ,
b0 #
b0 .
1&
#390000
0$
#395000
1$
#400000
0$
#405000
1$
#409000
0&
#410000
0$
#415000
b10 0
b1101 !
b1101 1
b1 ,
1$
#420000
0$
#425000
b1011 !
b1011 1
b11 0
b10 ,
1$
#430000
0$
#435000
b0 0
b111 !
b111 1
b11 ,
1$
#440000
0$
#445000
b1110 !
b1110 1
b1 0
b0 ,
1$
#450000
0$
#455000
b10 0
b1101 !
b1101 1
b1 ,
1$
#460000
0$
#465000
b1011 !
b1011 1
b11 0
b10 ,
1$
#470000
0$
#475000
b0 0
b111 !
b111 1
b11 ,
1$
#480000
0$
#485000
b1110 !
b1110 1
b1 0
b0 ,
1$
#490000
0$
#495000
b10 0
b1101 !
b1101 1
b1 ,
1$
#500000
0$
#505000
b1011 !
b1011 1
b11 0
b10 ,
1$
#510000
0$
#515000
b0 0
b111 !
b111 1
b11 ,
1$
#520000
0$
#525000
b1110 !
b1110 1
b1 0
b0 ,
1$
#530000
0$
#535000
b10 0
b1101 !
b1101 1
b1 ,
1$
#540000
0$
#545000
b1011 !
b1011 1
b11 0
b10 ,
1$
